fscache/__init__.py
fscache/encoder.py
fscache/fscache.py
fscache-0.4.0.dist-info/AUTHORS.rst
fscache-0.4.0.dist-info/LICENSE
fscache-0.4.0.dist-info/METADATA
fscache-0.4.0.dist-info/WHEEL
fscache-0.4.0.dist-info/top_level.txt
fscache-0.4.0.dist-info/RECORD
