Metadata-Version: 2.1
Name: fscache
Version: 0.4.0
Summary: A Python package for caching data in the file system.
Home-page: https://github.com/yaph/fscache
Author: Ramiro Gómez
Author-email: code@ramiro.org
License: MIT license
Keywords: cache,caching,file system
Classifier: Development Status :: 4 - Beta
Classifier: Intended Audience :: Developers
Classifier: License :: OSI Approved :: MIT License
Classifier: Natural Language :: English
Classifier: Programming Language :: Python :: 3
Classifier: Programming Language :: Python :: 3.6
Classifier: Programming Language :: Python :: 3.7
License-File: LICENSE
License-File: AUTHORS.rst
